django_mail_engin_pkg/__init__.py
django_mail_engin_pkg/asgi.py
django_mail_engin_pkg/settings.py
django_mail_engin_pkg/urls.py
django_mail_engin_pkg/wsgi.py
sit_django_mail/__init__.py
sit_django_mail/admin.py
sit_django_mail/apps.py
sit_django_mail/models.py
sit_django_mail/tests.py
sit_django_mail/views.py
sit_django_mail/migrations/__init__.py
sit_django_mailx-0.0.2.dist-info/LICENSE
sit_django_mailx-0.0.2.dist-info/METADATA
sit_django_mailx-0.0.2.dist-info/WHEEL
sit_django_mailx-0.0.2.dist-info/top_level.txt
sit_django_mailx-0.0.2.dist-info/RECORD
